{
  "anchors": [
    {
      "id": "0x6762",
      "anchorPos": {
        "x": 0,
        "y": 0,
        "z": 750
      }
    },
    {
      "id": "0x6706",
      "anchorPos": {
        "x": 123,
        "y": 123,
        "z": 1640
      }
    },
    {
      "id": "0x6E2F",
      "anchorPos": {
        "x": 123,
        "y": 123,
        "z": 950
      }
    },
    {
      "id": "0x672F",
      "anchorPos": {
        "x": 123,
        "y": 123,
        "z": 1250
      }
    }
  ],
  "tags": [
    {
      "id": "0x6740"
    }
  ],
  "trafficLights": [
    {
      "id": "60f58d873472f42f28d9844c",
      "pos": {
        "x": 123,
        "y": 123
      }
    },
    {
      "id": "60f58d933472f42f28d98451",
      "pos": {
        "x": 123,
        "y": 123
      }
    }
  ]
}